README.rst
setup.py
django_sequere.egg-info/PKG-INFO
django_sequere.egg-info/SOURCES.txt
django_sequere.egg-info/dependency_links.txt
django_sequere.egg-info/not-zip-safe
django_sequere.egg-info/requires.txt
django_sequere.egg-info/top_level.txt
sequere/__init__.py
sequere/app.py
sequere/apps.py
sequere/base.py
sequere/compat.py
sequere/defaults.py
sequere/exceptions.py
sequere/helpers.py
sequere/mixin.py
sequere/models.py
sequere/query.py
sequere/registry.py
sequere/signals.py
sequere/urls.py
sequere/utils.py
sequere/views.py
sequere/backends/__init__.py
sequere/backends/base.py
sequere/backends/database/__init__.py
sequere/backends/database/backend.py
sequere/backends/database/models.py
sequere/backends/database/query.py
sequere/backends/redis/__init__.py
sequere/backends/redis/backend.py
sequere/backends/redis/managers.py
sequere/backends/redis/models.py
sequere/backends/redis/query.py
sequere/backends/redis/utils.py
sequere/contrib/__init__.py
sequere/contrib/timeline/__init__.py
sequere/contrib/timeline/action.py
sequere/contrib/timeline/app.py
sequere/contrib/timeline/apps.py
sequere/contrib/timeline/exceptions.py
sequere/contrib/timeline/models.py
sequere/contrib/timeline/signals.py
sequere/contrib/timeline/tasks.py
sequere/contrib/timeline/timeline.py
sequere/contrib/timeline/utils.py
sequere/contrib/timeline/backends/__init__.py
sequere/contrib/timeline/backends/base.py
sequere/contrib/timeline/backends/redis/__init__.py
sequere/contrib/timeline/backends/redis/backend.py
sequere/contrib/timeline/backends/redis/query.py
sequere/contrib/user/__init__.py
sequere/contrib/user/models.py
sequere/contrib/user/sequere_registry.py
sequere/contrib/user/urls.py
sequere/contrib/user/views.py
sequere/templatetags/__init__.py
sequere/templatetags/sequere_tags.py
sequere/tests/__init__.py
sequere/tests/celery.py
sequere/tests/models.py
sequere/tests/sequere_registry.py
sequere/tests/settings.py
sequere/tests/tests.py
sequere/tests/urls.py