Metadata-Version: 1.1
Name: django-sequere
Version: 0.4.1
Summary: A Django application to implement a follow system and a timeline using multiple backends (db, redis, etc.)
Home-page: http://github.com/thoas/django-sequere
Author: Florent Messa
Author-email: florent.messa@gmail.com
License: UNKNOWN
Keywords: django,libraries,settings,redis,follow,timeline
Platform: any
Classifier: Environment :: Web Environment
Classifier: Intended Audience :: Developers
Classifier: License :: OSI Approved :: MIT License
Classifier: Operating System :: OS Independent
Classifier: Programming Language :: Python :: 2.6
Classifier: Programming Language :: Python :: 2.7
Classifier: Programming Language :: Python :: 3.3
Classifier: Topic :: Utilities
